<?xml version="1.0" encoding="UTF-8"?>
<network xmlns="http://sndlib.zib.de/network" xmlns:xsi="http://www.w3.org/2001/XMLSchema-instance" xsi:schemaLocation="http://sndlib.zib.de/network http://sndlib.zib.de/sndlib/network/network.xsd">
  <networkStructure>
    <nodes>
      <node id="n1_N03">
        <coordinates>
          <x>269.0</x>
          <y>20.0</y>
        </coordinates>
      </node>
      <node id="n1_N08">
        <coordinates>
          <x>397.0</x>
          <y>131.0</y>
        </coordinates>
      </node>
      <node id="n1_N09">
        <coordinates>
          <x>482.0</x>
          <y>137.0</y>
        </coordinates>
      </node>
      <node id="n1_N11">
        <coordinates>
          <x>41.0</x>
          <y>249.0</y>
        </coordinates>
      </node>
      <node id="n1_N13">
        <coordinates>
          <x>381.0</x>
          <y>250.0</y>
        </coordinates>
      </node>
      <node id="n1_N14">
        <coordinates>
          <x>378.0</x>
          <y>297.0</y>
        </coordinates>
      </node>
      <node id="n1_N15">
        <coordinates>
          <x>257.0</x>
          <y>303.0</y>
        </coordinates>
      </node>
      <node id="n1_N16">
        <coordinates>
          <x>184.0</x>
          <y>248.0</y>
        </coordinates>
      </node>
      <node id="n1_N18">
        <coordinates>
          <x>59.0</x>
          <y>293.0</y>
        </coordinates>
      </node>
      <node id="n1_N20">
        <coordinates>
          <x>176.0</x>
          <y>394.0</y>
        </coordinates>
      </node>
      <node id="n1_N21">
        <coordinates>
          <x>135.0</x>
          <y>333.0</y>
        </coordinates>
      </node>
      <node id="n1_N22">
        <coordinates>
          <x>413.0</x>
          <y>329.0</y>
        </coordinates>
      </node>
      <node id="n1_N23">
        <coordinates>
          <x>358.0</x>
          <y>394.0</y>
        </coordinates>
      </node>
      <node id="n1_N24">
        <coordinates>
          <x>268.0</x>
          <y>398.0</y>
        </coordinates>
      </node>
      <node id="n1_N25">
        <coordinates>
          <x>235.0</x>
          <y>188.0</y>
        </coordinates>
      </node>
      <node id="n2_N1">
        <coordinates>
          <x>237.0</x>
          <y>338.0</y>
        </coordinates>
      </node>
      <node id="n2_N12">
        <coordinates>
          <x>277.0</x>
          <y>70.0</y>
        </coordinates>
      </node>
      <node id="n2_N13">
        <coordinates>
          <x>540.0</x>
          <y>147.0</y>
        </coordinates>
      </node>
      <node id="n2_N15">
        <coordinates>
          <x>490.0</x>
          <y>349.0</y>
        </coordinates>
      </node>
      <node id="n2_N2">
        <coordinates>
          <x>130.0</x>
          <y>207.0</y>
        </coordinates>
      </node>
      <node id="n2_N5">
        <coordinates>
          <x>345.0</x>
          <y>232.0</y>
        </coordinates>
      </node>
      <node id="n2_N6">
        <coordinates>
          <x>95.0</x>
          <y>350.0</y>
        </coordinates>
      </node>
      <node id="n2_N7">
        <coordinates>
          <x>302.0</x>
          <y>404.0</y>
        </coordinates>
      </node>
      <node id="n2_N8">
        <coordinates>
          <x>161.0</x>
          <y>454.0</y>
        </coordinates>
      </node>
    </nodes>
    <links>
      <link id="inter_n1_N09_n2_N12">
        <source>n1_N09</source>
        <target>n2_N12</target>
        <setupCost>32.0</setupCost>
        <additionalModules>
          <addModule>
            <capacity>2500.0</capacity>
            <cost>20.0</cost>
          </addModule>
        </additionalModules>
      </link>
      <link id="inter_n1_N15_n2_N1">
        <source>n1_N15</source>
        <target>n2_N1</target>
        <setupCost>32.0</setupCost>
        <additionalModules>
          <addModule>
            <capacity>2500.0</capacity>
            <cost>20.0</cost>
          </addModule>
        </additionalModules>
      </link>
      <link id="inter_n1_N22_n2_N13">
        <source>n1_N22</source>
        <target>n2_N13</target>
        <setupCost>32.0</setupCost>
        <additionalModules>
          <addModule>
            <capacity>2500.0</capacity>
            <cost>20.0</cost>
          </addModule>
        </additionalModules>
      </link>
      <link id="inter_n2_N12_n1_N09">
        <source>n2_N12</source>
        <target>n1_N09</target>
        <setupCost>32.0</setupCost>
        <additionalModules>
          <addModule>
            <capacity>2500.0</capacity>
            <cost>20.0</cost>
          </addModule>
        </additionalModules>
      </link>
      <link id="inter_n2_N13_n1_N22">
        <source>n2_N13</source>
        <target>n1_N22</target>
        <setupCost>32.0</setupCost>
        <additionalModules>
          <addModule>
            <capacity>2500.0</capacity>
            <cost>20.0</cost>
          </addModule>
        </additionalModules>
      </link>
      <link id="inter_n2_N1_n1_N15">
        <source>n2_N1</source>
        <target>n1_N15</target>
        <setupCost>32.0</setupCost>
        <additionalModules>
          <addModule>
            <capacity>2500.0</capacity>
            <cost>20.0</cost>
          </addModule>
        </additionalModules>
      </link>
      <link id="n1_LinkN03_N09">
        <source>n1_N03</source>
        <target>n1_N09</target>
        <setupCost>414.5</setupCost>
        <additionalModules>
          <addModule>
            <capacity>2500.0</capacity>
            <cost>20.0</cost>
          </addModule>
        </additionalModules>
      </link>
      <link id="n1_LinkN08_N09">
        <source>n1_N08</source>
        <target>n1_N09</target>
        <setupCost>115.4</setupCost>
        <additionalModules>
          <addModule>
            <capacity>2500.0</capacity>
            <cost>20.0</cost>
          </addModule>
        </additionalModules>
      </link>
      <link id="n1_LinkN13_N14">
        <source>n1_N13</source>
        <target>n1_N14</target>
        <setupCost>50.2</setupCost>
        <additionalModules>
          <addModule>
            <capacity>2500.0</capacity>
            <cost>20.0</cost>
          </addModule>
        </additionalModules>
      </link>
      <link id="n1_LinkN15_N09">
        <source>n1_N15</source>
        <target>n1_N09</target>
        <setupCost>578.5</setupCost>
        <additionalModules>
          <addModule>
            <capacity>2500.0</capacity>
            <cost>20.0</cost>
          </addModule>
        </additionalModules>
      </link>
      <link id="n1_LinkN15_N11">
        <source>n1_N15</source>
        <target>n1_N11</target>
        <setupCost>962.8000000000001</setupCost>
        <additionalModules>
          <addModule>
            <capacity>2500.0</capacity>
            <cost>20.0</cost>
          </addModule>
        </additionalModules>
      </link>
      <link id="n1_LinkN15_N13">
        <source>n1_N15</source>
        <target>n1_N13</target>
        <setupCost>103.10000000000001</setupCost>
        <additionalModules>
          <addModule>
            <capacity>2500.0</capacity>
            <cost>20.0</cost>
          </addModule>
        </additionalModules>
      </link>
      <link id="n1_LinkN15_N14">
        <source>n1_N15</source>
        <target>n1_N14</target>
        <setupCost>82.9</setupCost>
        <additionalModules>
          <addModule>
            <capacity>2500.0</capacity>
            <cost>20.0</cost>
          </addModule>
        </additionalModules>
      </link>
      <link id="n1_LinkN15_N16">
        <source>n1_N15</source>
        <target>n1_N16</target>
        <setupCost>10.0</setupCost>
        <additionalModules>
          <addModule>
            <capacity>2500.0</capacity>
            <cost>20.0</cost>
          </addModule>
        </additionalModules>
      </link>
      <link id="n1_LinkN15_N18">
        <source>n1_N15</source>
        <target>n1_N18</target>
        <setupCost>40.300000000000004</setupCost>
        <additionalModules>
          <addModule>
            <capacity>2500.0</capacity>
            <cost>20.0</cost>
          </addModule>
        </additionalModules>
      </link>
      <link id="n1_LinkN15_N20">
        <source>n1_N15</source>
        <target>n1_N20</target>
        <setupCost>46.800000000000004</setupCost>
        <additionalModules>
          <addModule>
            <capacity>2500.0</capacity>
            <cost>20.0</cost>
          </addModule>
        </additionalModules>
      </link>
      <link id="n1_LinkN15_N21">
        <source>n1_N15</source>
        <target>n1_N21</target>
        <setupCost>136.8</setupCost>
        <additionalModules>
          <addModule>
            <capacity>2500.0</capacity>
            <cost>20.0</cost>
          </addModule>
        </additionalModules>
      </link>
      <link id="n1_LinkN15_N22">
        <source>n1_N15</source>
        <target>n1_N22</target>
        <setupCost>32.0</setupCost>
        <additionalModules>
          <addModule>
            <capacity>2500.0</capacity>
            <cost>20.0</cost>
          </addModule>
        </additionalModules>
      </link>
      <link id="n1_LinkN15_N25">
        <source>n1_N15</source>
        <target>n1_N25</target>
        <setupCost>696.2</setupCost>
        <additionalModules>
          <addModule>
            <capacity>2500.0</capacity>
            <cost>20.0</cost>
          </addModule>
        </additionalModules>
      </link>
      <link id="n1_LinkN16_N09">
        <source>n1_N16</source>
        <target>n1_N09</target>
        <setupCost>957.6</setupCost>
        <additionalModules>
          <addModule>
            <capacity>2500.0</capacity>
            <cost>20.0</cost>
          </addModule>
        </additionalModules>
      </link>
      <link id="n1_LinkN16_N11">
        <source>n1_N16</source>
        <target>n1_N11</target>
        <setupCost>125.0</setupCost>
        <additionalModules>
          <addModule>
            <capacity>2500.0</capacity>
            <cost>20.0</cost>
          </addModule>
        </additionalModules>
      </link>
      <link id="n1_LinkN20_N21">
        <source>n1_N20</source>
        <target>n1_N21</target>
        <setupCost>90.10000000000001</setupCost>
        <additionalModules>
          <addModule>
            <capacity>2500.0</capacity>
            <cost>20.0</cost>
          </addModule>
        </additionalModules>
      </link>
      <link id="n1_LinkN20_N24">
        <source>n1_N20</source>
        <target>n1_N24</target>
        <setupCost>36.4</setupCost>
        <additionalModules>
          <addModule>
            <capacity>2500.0</capacity>
            <cost>20.0</cost>
          </addModule>
        </additionalModules>
      </link>
      <link id="n1_LinkN22_N09">
        <source>n1_N22</source>
        <target>n1_N09</target>
        <setupCost>557.2</setupCost>
        <additionalModules>
          <addModule>
            <capacity>2500.0</capacity>
            <cost>20.0</cost>
          </addModule>
        </additionalModules>
      </link>
      <link id="n1_LinkN22_N20">
        <source>n1_N22</source>
        <target>n1_N20</target>
        <setupCost>62.900000000000006</setupCost>
        <additionalModules>
          <addModule>
            <capacity>2500.0</capacity>
            <cost>20.0</cost>
          </addModule>
        </additionalModules>
      </link>
      <link id="n1_LinkN22_N23">
        <source>n1_N22</source>
        <target>n1_N23</target>
        <setupCost>31.8</setupCost>
        <additionalModules>
          <addModule>
            <capacity>2500.0</capacity>
            <cost>20.0</cost>
          </addModule>
        </additionalModules>
      </link>
      <link id="n1_LinkN22_N24">
        <source>n1_N22</source>
        <target>n1_N24</target>
        <setupCost>35.2</setupCost>
        <additionalModules>
          <addModule>
            <capacity>2500.0</capacity>
            <cost>20.0</cost>
          </addModule>
        </additionalModules>
      </link>
      <link id="n1_LinkN24_N23">
        <source>n1_N24</source>
        <target>n1_N23</target>
        <setupCost>17.6</setupCost>
        <additionalModules>
          <addModule>
            <capacity>2500.0</capacity>
            <cost>20.0</cost>
          </addModule>
        </additionalModules>
      </link>
      <link id="n1_LinkN25_N03">
        <source>n1_N25</source>
        <target>n1_N03</target>
        <setupCost>310.0</setupCost>
        <additionalModules>
          <addModule>
            <capacity>2500.0</capacity>
            <cost>20.0</cost>
          </addModule>
        </additionalModules>
      </link>
      <link id="n1_LinkN25_N09">
        <source>n1_N25</source>
        <target>n1_N09</target>
        <setupCost>120.0</setupCost>
        <additionalModules>
          <addModule>
            <capacity>2500.0</capacity>
            <cost>20.0</cost>
          </addModule>
        </additionalModules>
      </link>
      <link id="n2_L1">
        <source>n2_N1</source>
        <target>n2_N2</target>
        <routingCost>0.2</routingCost>
        <additionalModules>
          <addModule>
            <capacity>1000.0</capacity>
            <cost>4440.0</cost>
          </addModule>
          <addModule>
            <capacity>4000.0</capacity>
            <cost>5440.0</cost>
          </addModule>
        </additionalModules>
      </link>
      <link id="n2_L10">
        <source>n2_N2</source>
        <target>n2_N6</target>
        <routingCost>0.2</routingCost>
        <additionalModules>
          <addModule>
            <capacity>1000.0</capacity>
            <cost>5960.0</cost>
          </addModule>
          <addModule>
            <capacity>4000.0</capacity>
            <cost>6960.0</cost>
          </addModule>
        </additionalModules>
      </link>
      <link id="n2_L11">
        <source>n2_N2</source>
        <target>n2_N12</target>
        <routingCost>0.2</routingCost>
        <additionalModules>
          <addModule>
            <capacity>1000.0</capacity>
            <cost>7480.0</cost>
          </addModule>
          <addModule>
            <capacity>4000.0</capacity>
            <cost>8480.0</cost>
          </addModule>
        </additionalModules>
      </link>
      <link id="n2_L12">
        <source>n2_N2</source>
        <target>n2_N13</target>
        <routingCost>0.2</routingCost>
        <additionalModules>
          <addModule>
            <capacity>1000.0</capacity>
            <cost>10520.0</cost>
          </addModule>
          <addModule>
            <capacity>4000.0</capacity>
            <cost>11520.0</cost>
          </addModule>
        </additionalModules>
      </link>
      <link id="n2_L13">
        <source>n2_N2</source>
        <target>n2_N15</target>
        <routingCost>0.2</routingCost>
        <additionalModules>
          <addModule>
            <capacity>1000.0</capacity>
            <cost>10520.0</cost>
          </addModule>
          <addModule>
            <capacity>4000.0</capacity>
            <cost>11520.0</cost>
          </addModule>
        </additionalModules>
      </link>
      <link id="n2_L2">
        <source>n2_N1</source>
        <target>n2_N5</target>
        <routingCost>0.2</routingCost>
        <additionalModules>
          <addModule>
            <capacity>1000.0</capacity>
            <cost>5960.0</cost>
          </addModule>
          <addModule>
            <capacity>4000.0</capacity>
            <cost>6960.0</cost>
          </addModule>
        </additionalModules>
      </link>
      <link id="n2_L24">
        <source>n2_N5</source>
        <target>n2_N12</target>
        <routingCost>0.2</routingCost>
        <additionalModules>
          <addModule>
            <capacity>1000.0</capacity>
            <cost>5960.0</cost>
          </addModule>
          <addModule>
            <capacity>4000.0</capacity>
            <cost>6960.0</cost>
          </addModule>
        </additionalModules>
      </link>
      <link id="n2_L25">
        <source>n2_N5</source>
        <target>n2_N13</target>
        <routingCost>0.2</routingCost>
        <additionalModules>
          <addModule>
            <capacity>1000.0</capacity>
            <cost>9000.0</cost>
          </addModule>
          <addModule>
            <capacity>4000.0</capacity>
            <cost>10000.0</cost>
          </addModule>
        </additionalModules>
      </link>
      <link id="n2_L26">
        <source>n2_N5</source>
        <target>n2_N15</target>
        <routingCost>0.2</routingCost>
        <additionalModules>
          <addModule>
            <capacity>1000.0</capacity>
            <cost>10520.0</cost>
          </addModule>
          <addModule>
            <capacity>4000.0</capacity>
            <cost>11520.0</cost>
          </addModule>
        </additionalModules>
      </link>
      <link id="n2_L27">
        <source>n2_N6</source>
        <target>n2_N7</target>
        <routingCost>0.2</routingCost>
        <additionalModules>
          <addModule>
            <capacity>1000.0</capacity>
            <cost>5960.0</cost>
          </addModule>
          <addModule>
            <capacity>4000.0</capacity>
            <cost>6960.0</cost>
          </addModule>
        </additionalModules>
      </link>
      <link id="n2_L28">
        <source>n2_N6</source>
        <target>n2_N8</target>
        <routingCost>0.2</routingCost>
        <additionalModules>
          <addModule>
            <capacity>1000.0</capacity>
            <cost>4440.0</cost>
          </addModule>
          <addModule>
            <capacity>4000.0</capacity>
            <cost>5440.0</cost>
          </addModule>
        </additionalModules>
      </link>
      <link id="n2_L29">
        <source>n2_N7</source>
        <target>n2_N8</target>
        <routingCost>0.2</routingCost>
        <additionalModules>
          <addModule>
            <capacity>1000.0</capacity>
            <cost>4440.0</cost>
          </addModule>
          <addModule>
            <capacity>4000.0</capacity>
            <cost>5440.0</cost>
          </addModule>
        </additionalModules>
      </link>
      <link id="n2_L3">
        <source>n2_N1</source>
        <target>n2_N6</target>
        <routingCost>0.2</routingCost>
        <additionalModules>
          <addModule>
            <capacity>1000.0</capacity>
            <cost>5960.0</cost>
          </addModule>
          <addModule>
            <capacity>4000.0</capacity>
            <cost>6960.0</cost>
          </addModule>
        </additionalModules>
      </link>
      <link id="n2_L32">
        <source>n2_N7</source>
        <target>n2_N12</target>
        <routingCost>0.2</routingCost>
        <additionalModules>
          <addModule>
            <capacity>1000.0</capacity>
            <cost>12040.0</cost>
          </addModule>
          <addModule>
            <capacity>4000.0</capacity>
            <cost>13040.0</cost>
          </addModule>
        </additionalModules>
      </link>
      <link id="n2_L33">
        <source>n2_N7</source>
        <target>n2_N13</target>
        <routingCost>0.2</routingCost>
        <additionalModules>
          <addModule>
            <capacity>1000.0</capacity>
            <cost>13560.0</cost>
          </addModule>
          <addModule>
            <capacity>4000.0</capacity>
            <cost>14560.0</cost>
          </addModule>
        </additionalModules>
      </link>
      <link id="n2_L35">
        <source>n2_N7</source>
        <target>n2_N15</target>
        <routingCost>0.2</routingCost>
        <additionalModules>
          <addModule>
            <capacity>1000.0</capacity>
            <cost>9000.0</cost>
          </addModule>
          <addModule>
            <capacity>4000.0</capacity>
            <cost>10000.0</cost>
          </addModule>
        </additionalModules>
      </link>
      <link id="n2_L4">
        <source>n2_N1</source>
        <target>n2_N7</target>
        <routingCost>0.2</routingCost>
        <additionalModules>
          <addModule>
            <capacity>1000.0</capacity>
            <cost>7480.0</cost>
          </addModule>
          <addModule>
            <capacity>4000.0</capacity>
            <cost>8480.0</cost>
          </addModule>
        </additionalModules>
      </link>
      <link id="n2_L44">
        <source>n2_N12</source>
        <target>n2_N13</target>
        <routingCost>0.2</routingCost>
        <additionalModules>
          <addModule>
            <capacity>1000.0</capacity>
            <cost>5960.0</cost>
          </addModule>
          <addModule>
            <capacity>4000.0</capacity>
            <cost>6960.0</cost>
          </addModule>
        </additionalModules>
      </link>
      <link id="n2_L45">
        <source>n2_N12</source>
        <target>n2_N15</target>
        <routingCost>0.2</routingCost>
        <additionalModules>
          <addModule>
            <capacity>1000.0</capacity>
            <cost>9000.0</cost>
          </addModule>
          <addModule>
            <capacity>4000.0</capacity>
            <cost>10000.0</cost>
          </addModule>
        </additionalModules>
      </link>
      <link id="n2_L47">
        <source>n2_N13</source>
        <target>n2_N15</target>
        <routingCost>0.2</routingCost>
        <additionalModules>
          <addModule>
            <capacity>1000.0</capacity>
            <cost>7480.0</cost>
          </addModule>
          <addModule>
            <capacity>4000.0</capacity>
            <cost>8480.0</cost>
          </addModule>
        </additionalModules>
      </link>
      <link id="n2_L5">
        <source>n2_N1</source>
        <target>n2_N8</target>
        <routingCost>0.2</routingCost>
        <additionalModules>
          <addModule>
            <capacity>1000.0</capacity>
            <cost>7480.0</cost>
          </addModule>
          <addModule>
            <capacity>4000.0</capacity>
            <cost>8480.0</cost>
          </addModule>
        </additionalModules>
      </link>
      <link id="n2_L6">
        <source>n2_N1</source>
        <target>n2_N12</target>
        <routingCost>0.2</routingCost>
        <additionalModules>
          <addModule>
            <capacity>1000.0</capacity>
            <cost>7480.0</cost>
          </addModule>
          <addModule>
            <capacity>4000.0</capacity>
            <cost>8480.0</cost>
          </addModule>
        </additionalModules>
      </link>
      <link id="n2_L7">
        <source>n2_N1</source>
        <target>n2_N13</target>
        <routingCost>0.2</routingCost>
        <additionalModules>
          <addModule>
            <capacity>1000.0</capacity>
            <cost>10520.0</cost>
          </addModule>
          <addModule>
            <capacity>4000.0</capacity>
            <cost>11520.0</cost>
          </addModule>
        </additionalModules>
      </link>
      <link id="n2_L8">
        <source>n2_N1</source>
        <target>n2_N15</target>
        <routingCost>0.2</routingCost>
        <additionalModules>
          <addModule>
            <capacity>1000.0</capacity>
            <cost>9000.0</cost>
          </addModule>
          <addModule>
            <capacity>4000.0</capacity>
            <cost>10000.0</cost>
          </addModule>
        </additionalModules>
      </link>
      <link id="n2_L9">
        <source>n2_N2</source>
        <target>n2_N5</target>
        <routingCost>0.2</routingCost>
        <additionalModules>
          <addModule>
            <capacity>1000.0</capacity>
            <cost>2920.0</cost>
          </addModule>
          <addModule>
            <capacity>4000.0</capacity>
            <cost>3920.0</cost>
          </addModule>
        </additionalModules>
      </link>
    </links>
  </networkStructure>
  <demands>
    <demand id="n1_DemN03_N11">
      <source>n1_N03</source>
      <target>n1_N11</target>
      <demandValue>155.0</demandValue>
    </demand>
    <demand id="n1_DemN03_N16">
      <source>n1_N03</source>
      <target>n1_N16</target>
      <demandValue>437.0</demandValue>
    </demand>
    <demand id="n1_DemN03_N20">
      <source>n1_N03</source>
      <target>n1_N20</target>
      <demandValue>437.0</demandValue>
    </demand>
    <demand id="n1_DemN03_N24">
      <source>n1_N03</source>
      <target>n1_N24</target>
      <demandValue>486.0</demandValue>
    </demand>
    <demand id="n1_DemN08_N03">
      <source>n1_N08</source>
      <target>n1_N03</target>
      <demandValue>155.0</demandValue>
    </demand>
    <demand id="n1_DemN08_N09">
      <source>n1_N08</source>
      <target>n1_N09</target>
      <demandValue>408.0</demandValue>
    </demand>
    <demand id="n1_DemN08_N11">
      <source>n1_N08</source>
      <target>n1_N11</target>
      <demandValue>116.0</demandValue>
    </demand>
    <demand id="n1_DemN08_N13">
      <source>n1_N08</source>
      <target>n1_N13</target>
      <demandValue>155.0</demandValue>
    </demand>
    <demand id="n1_DemN08_N14">
      <source>n1_N08</source>
      <target>n1_N14</target>
      <demandValue>77.0</demandValue>
    </demand>
    <demand id="n1_DemN08_N15">
      <source>n1_N08</source>
      <target>n1_N15</target>
      <demandValue>486.0</demandValue>
    </demand>
    <demand id="n1_DemN08_N16">
      <source>n1_N08</source>
      <target>n1_N16</target>
      <demandValue>320.0</demandValue>
    </demand>
    <demand id="n1_DemN08_N20">
      <source>n1_N08</source>
      <target>n1_N20</target>
      <demandValue>320.0</demandValue>
    </demand>
    <demand id="n1_DemN08_N22">
      <source>n1_N08</source>
      <target>n1_N22</target>
      <demandValue>447.0</demandValue>
    </demand>
    <demand id="n1_DemN08_N23">
      <source>n1_N08</source>
      <target>n1_N23</target>
      <demandValue>282.0</demandValue>
    </demand>
    <demand id="n1_DemN09_N03">
      <source>n1_N09</source>
      <target>n1_N03</target>
      <demandValue>544.0</demandValue>
    </demand>
    <demand id="n1_DemN09_N11">
      <source>n1_N09</source>
      <target>n1_N11</target>
      <demandValue>408.0</demandValue>
    </demand>
    <demand id="n1_DemN09_N13">
      <source>n1_N09</source>
      <target>n1_N13</target>
      <demandValue>544.0</demandValue>
    </demand>
    <demand id="n1_DemN09_N14">
      <source>n1_N09</source>
      <target>n1_N14</target>
      <demandValue>272.0</demandValue>
    </demand>
    <demand id="n1_DemN09_N20">
      <source>n1_N09</source>
      <target>n1_N20</target>
      <demandValue>1098.0</demandValue>
    </demand>
    <demand id="n1_DemN09_N22">
      <source>n1_N09</source>
      <target>n1_N22</target>
      <demandValue>1507.0</demandValue>
    </demand>
    <demand id="n1_DemN09_N23">
      <source>n1_N09</source>
      <target>n1_N23</target>
      <demandValue>953.0</demandValue>
    </demand>
    <demand id="n1_DemN09_N24">
      <source>n1_N09</source>
      <target>n1_N24</target>
      <demandValue>1235.0</demandValue>
    </demand>
    <demand id="n1_DemN09_N25">
      <source>n1_N09</source>
      <target>n1_N25</target>
      <demandValue>544.0</demandValue>
    </demand>
    <demand id="n1_DemN11_N15">
      <source>n1_N11</source>
      <target>n1_N15</target>
      <demandValue>486.0</demandValue>
    </demand>
    <demand id="n1_DemN11_N16">
      <source>n1_N11</source>
      <target>n1_N16</target>
      <demandValue>320.0</demandValue>
    </demand>
    <demand id="n1_DemN11_N21">
      <source>n1_N11</source>
      <target>n1_N21</target>
      <demandValue>77.0</demandValue>
    </demand>
    <demand id="n1_DemN11_N22">
      <source>n1_N11</source>
      <target>n1_N22</target>
      <demandValue>447.0</demandValue>
    </demand>
    <demand id="n1_DemN11_N23">
      <source>n1_N11</source>
      <target>n1_N23</target>
      <demandValue>282.0</demandValue>
    </demand>
    <demand id="n1_DemN11_N24">
      <source>n1_N11</source>
      <target>n1_N24</target>
      <demandValue>369.0</demandValue>
    </demand>
    <demand id="n1_DemN13_N03">
      <source>n1_N13</source>
      <target>n1_N03</target>
      <demandValue>213.0</demandValue>
    </demand>
    <demand id="n1_DemN13_N11">
      <source>n1_N13</source>
      <target>n1_N11</target>
      <demandValue>155.0</demandValue>
    </demand>
    <demand id="n1_DemN13_N16">
      <source>n1_N13</source>
      <target>n1_N16</target>
      <demandValue>437.0</demandValue>
    </demand>
    <demand id="n1_DemN13_N18">
      <source>n1_N13</source>
      <target>n1_N18</target>
      <demandValue>272.0</demandValue>
    </demand>
    <demand id="n1_DemN13_N22">
      <source>n1_N13</source>
      <target>n1_N22</target>
      <demandValue>602.0</demandValue>
    </demand>
    <demand id="n1_DemN13_N24">
      <source>n1_N13</source>
      <target>n1_N24</target>
      <demandValue>486.0</demandValue>
    </demand>
    <demand id="n1_DemN14_N03">
      <source>n1_N14</source>
      <target>n1_N03</target>
      <demandValue>106.0</demandValue>
    </demand>
    <demand id="n1_DemN14_N11">
      <source>n1_N14</source>
      <target>n1_N11</target>
      <demandValue>77.0</demandValue>
    </demand>
    <demand id="n1_DemN14_N13">
      <source>n1_N14</source>
      <target>n1_N13</target>
      <demandValue>106.0</demandValue>
    </demand>
    <demand id="n1_DemN14_N15">
      <source>n1_N14</source>
      <target>n1_N15</target>
      <demandValue>320.0</demandValue>
    </demand>
    <demand id="n1_DemN14_N16">
      <source>n1_N14</source>
      <target>n1_N16</target>
      <demandValue>213.0</demandValue>
    </demand>
    <demand id="n1_DemN14_N18">
      <source>n1_N14</source>
      <target>n1_N18</target>
      <demandValue>136.0</demandValue>
    </demand>
    <demand id="n1_DemN14_N20">
      <source>n1_N14</source>
      <target>n1_N20</target>
      <demandValue>213.0</demandValue>
    </demand>
    <demand id="n1_DemN14_N21">
      <source>n1_N14</source>
      <target>n1_N21</target>
      <demandValue>48.0</demandValue>
    </demand>
    <demand id="n1_DemN14_N25">
      <source>n1_N14</source>
      <target>n1_N25</target>
      <demandValue>106.0</demandValue>
    </demand>
    <demand id="n1_DemN15_N03">
      <source>n1_N15</source>
      <target>n1_N03</target>
      <demandValue>651.0</demandValue>
    </demand>
    <demand id="n1_DemN15_N09">
      <source>n1_N15</source>
      <target>n1_N09</target>
      <demandValue>1643.0</demandValue>
    </demand>
    <demand id="n1_DemN15_N13">
      <source>n1_N15</source>
      <target>n1_N13</target>
      <demandValue>651.0</demandValue>
    </demand>
    <demand id="n1_DemN15_N16">
      <source>n1_N15</source>
      <target>n1_N16</target>
      <demandValue>1312.0</demandValue>
    </demand>
    <demand id="n1_DemN15_N18">
      <source>n1_N15</source>
      <target>n1_N18</target>
      <demandValue>816.0</demandValue>
    </demand>
    <demand id="n1_DemN15_N21">
      <source>n1_N15</source>
      <target>n1_N21</target>
      <demandValue>320.0</demandValue>
    </demand>
    <demand id="n1_DemN15_N24">
      <source>n1_N15</source>
      <target>n1_N24</target>
      <demandValue>1478.0</demandValue>
    </demand>
    <demand id="n1_DemN15_N25">
      <source>n1_N15</source>
      <target>n1_N25</target>
      <demandValue>651.0</demandValue>
    </demand>
    <demand id="n1_DemN16_N09">
      <source>n1_N16</source>
      <target>n1_N09</target>
      <demandValue>1098.0</demandValue>
    </demand>
    <demand id="n1_DemN16_N20">
      <source>n1_N16</source>
      <target>n1_N20</target>
      <demandValue>875.0</demandValue>
    </demand>
    <demand id="n1_DemN16_N25">
      <source>n1_N16</source>
      <target>n1_N25</target>
      <demandValue>437.0</demandValue>
    </demand>
    <demand id="n1_DemN18_N03">
      <source>n1_N18</source>
      <target>n1_N03</target>
      <demandValue>272.0</demandValue>
    </demand>
    <demand id="n1_DemN18_N08">
      <source>n1_N18</source>
      <target>n1_N08</target>
      <demandValue>204.0</demandValue>
    </demand>
    <demand id="n1_DemN18_N09">
      <source>n1_N18</source>
      <target>n1_N09</target>
      <demandValue>680.0</demandValue>
    </demand>
    <demand id="n1_DemN18_N11">
      <source>n1_N18</source>
      <target>n1_N11</target>
      <demandValue>204.0</demandValue>
    </demand>
    <demand id="n1_DemN18_N16">
      <source>n1_N18</source>
      <target>n1_N16</target>
      <demandValue>544.0</demandValue>
    </demand>
    <demand id="n1_DemN18_N21">
      <source>n1_N18</source>
      <target>n1_N21</target>
      <demandValue>136.0</demandValue>
    </demand>
    <demand id="n1_DemN20_N11">
      <source>n1_N20</source>
      <target>n1_N11</target>
      <demandValue>320.0</demandValue>
    </demand>
    <demand id="n1_DemN20_N13">
      <source>n1_N20</source>
      <target>n1_N13</target>
      <demandValue>437.0</demandValue>
    </demand>
    <demand id="n1_DemN20_N15">
      <source>n1_N20</source>
      <target>n1_N15</target>
      <demandValue>1312.0</demandValue>
    </demand>
    <demand id="n1_DemN20_N18">
      <source>n1_N20</source>
      <target>n1_N18</target>
      <demandValue>544.0</demandValue>
    </demand>
    <demand id="n1_DemN20_N21">
      <source>n1_N20</source>
      <target>n1_N21</target>
      <demandValue>213.0</demandValue>
    </demand>
    <demand id="n1_DemN20_N24">
      <source>n1_N20</source>
      <target>n1_N24</target>
      <demandValue>982.0</demandValue>
    </demand>
    <demand id="n1_DemN20_N25">
      <source>n1_N20</source>
      <target>n1_N25</target>
      <demandValue>437.0</demandValue>
    </demand>
    <demand id="n1_DemN21_N03">
      <source>n1_N21</source>
      <target>n1_N03</target>
      <demandValue>106.0</demandValue>
    </demand>
    <demand id="n1_DemN21_N08">
      <source>n1_N21</source>
      <target>n1_N08</target>
      <demandValue>77.0</demandValue>
    </demand>
    <demand id="n1_DemN21_N09">
      <source>n1_N21</source>
      <target>n1_N09</target>
      <demandValue>272.0</demandValue>
    </demand>
    <demand id="n1_DemN21_N13">
      <source>n1_N21</source>
      <target>n1_N13</target>
      <demandValue>106.0</demandValue>
    </demand>
    <demand id="n1_DemN21_N16">
      <source>n1_N21</source>
      <target>n1_N16</target>
      <demandValue>213.0</demandValue>
    </demand>
    <demand id="n1_DemN21_N22">
      <source>n1_N21</source>
      <target>n1_N22</target>
      <demandValue>301.0</demandValue>
    </demand>
    <demand id="n1_DemN21_N24">
      <source>n1_N21</source>
      <target>n1_N24</target>
      <demandValue>243.0</demandValue>
    </demand>
    <demand id="n1_DemN22_N03">
      <source>n1_N22</source>
      <target>n1_N03</target>
      <demandValue>602.0</demandValue>
    </demand>
    <demand id="n1_DemN22_N14">
      <source>n1_N22</source>
      <target>n1_N14</target>
      <demandValue>301.0</demandValue>
    </demand>
    <demand id="n1_DemN22_N15">
      <source>n1_N22</source>
      <target>n1_N15</target>
      <demandValue>1808.0</demandValue>
    </demand>
    <demand id="n1_DemN22_N16">
      <source>n1_N22</source>
      <target>n1_N16</target>
      <demandValue>1205.0</demandValue>
    </demand>
    <demand id="n1_DemN22_N18">
      <source>n1_N22</source>
      <target>n1_N18</target>
      <demandValue>748.0</demandValue>
    </demand>
    <demand id="n1_DemN22_N20">
      <source>n1_N22</source>
      <target>n1_N20</target>
      <demandValue>1205.0</demandValue>
    </demand>
    <demand id="n1_DemN23_N03">
      <source>n1_N23</source>
      <target>n1_N03</target>
      <demandValue>379.0</demandValue>
    </demand>
    <demand id="n1_DemN23_N13">
      <source>n1_N23</source>
      <target>n1_N13</target>
      <demandValue>379.0</demandValue>
    </demand>
    <demand id="n1_DemN23_N14">
      <source>n1_N23</source>
      <target>n1_N14</target>
      <demandValue>184.0</demandValue>
    </demand>
    <demand id="n1_DemN23_N15">
      <source>n1_N23</source>
      <target>n1_N15</target>
      <demandValue>1147.0</demandValue>
    </demand>
    <demand id="n1_DemN23_N16">
      <source>n1_N23</source>
      <target>n1_N16</target>
      <demandValue>768.0</demandValue>
    </demand>
    <demand id="n1_DemN23_N18">
      <source>n1_N23</source>
      <target>n1_N18</target>
      <demandValue>476.0</demandValue>
    </demand>
    <demand id="n1_DemN23_N20">
      <source>n1_N23</source>
      <target>n1_N20</target>
      <demandValue>768.0</demandValue>
    </demand>
    <demand id="n1_DemN23_N21">
      <source>n1_N23</source>
      <target>n1_N21</target>
      <demandValue>184.0</demandValue>
    </demand>
    <demand id="n1_DemN23_N22">
      <source>n1_N23</source>
      <target>n1_N22</target>
      <demandValue>1050.0</demandValue>
    </demand>
    <demand id="n1_DemN23_N24">
      <source>n1_N23</source>
      <target>n1_N24</target>
      <demandValue>865.0</demandValue>
    </demand>
    <demand id="n1_DemN24_N08">
      <source>n1_N24</source>
      <target>n1_N08</target>
      <demandValue>369.0</demandValue>
    </demand>
    <demand id="n1_DemN24_N14">
      <source>n1_N24</source>
      <target>n1_N14</target>
      <demandValue>243.0</demandValue>
    </demand>
    <demand id="n1_DemN24_N16">
      <source>n1_N24</source>
      <target>n1_N16</target>
      <demandValue>982.0</demandValue>
    </demand>
    <demand id="n1_DemN24_N18">
      <source>n1_N24</source>
      <target>n1_N18</target>
      <demandValue>612.0</demandValue>
    </demand>
    <demand id="n1_DemN24_N22">
      <source>n1_N24</source>
      <target>n1_N22</target>
      <demandValue>1361.0</demandValue>
    </demand>
    <demand id="n1_DemN24_N25">
      <source>n1_N24</source>
      <target>n1_N25</target>
      <demandValue>486.0</demandValue>
    </demand>
    <demand id="n1_DemN25_N03">
      <source>n1_N25</source>
      <target>n1_N03</target>
      <demandValue>213.0</demandValue>
    </demand>
    <demand id="n1_DemN25_N08">
      <source>n1_N25</source>
      <target>n1_N08</target>
      <demandValue>155.0</demandValue>
    </demand>
    <demand id="n1_DemN25_N11">
      <source>n1_N25</source>
      <target>n1_N11</target>
      <demandValue>155.0</demandValue>
    </demand>
    <demand id="n1_DemN25_N13">
      <source>n1_N25</source>
      <target>n1_N13</target>
      <demandValue>213.0</demandValue>
    </demand>
    <demand id="n1_DemN25_N18">
      <source>n1_N25</source>
      <target>n1_N18</target>
      <demandValue>272.0</demandValue>
    </demand>
    <demand id="n1_DemN25_N21">
      <source>n1_N25</source>
      <target>n1_N21</target>
      <demandValue>106.0</demandValue>
    </demand>
    <demand id="n1_DemN25_N22">
      <source>n1_N25</source>
      <target>n1_N22</target>
      <demandValue>602.0</demandValue>
    </demand>
    <demand id="n1_DemN25_N23">
      <source>n1_N25</source>
      <target>n1_N23</target>
      <demandValue>379.0</demandValue>
    </demand>
    <demand id="n2_D1">
      <source>n2_N1</source>
      <target>n2_N2</target>
      <demandValue>42.0</demandValue>
    </demand>
    <demand id="n2_D101">
      <source>n2_N7</source>
      <target>n2_N12</target>
      <demandValue>5.0</demandValue>
    </demand>
    <demand id="n2_D102">
      <source>n2_N7</source>
      <target>n2_N13</target>
      <demandValue>2.0</demandValue>
    </demand>
    <demand id="n2_D104">
      <source>n2_N7</source>
      <target>n2_N15</target>
      <demandValue>5.0</demandValue>
    </demand>
    <demand id="n2_D106">
      <source>n2_N8</source>
      <target>n2_N1</target>
      <demandValue>9.0</demandValue>
    </demand>
    <demand id="n2_D107">
      <source>n2_N8</source>
      <target>n2_N2</target>
      <demandValue>6.0</demandValue>
    </demand>
    <demand id="n2_D11">
      <source>n2_N1</source>
      <target>n2_N12</target>
      <demandValue>17.0</demandValue>
    </demand>
    <demand id="n2_D110">
      <source>n2_N8</source>
      <target>n2_N5</target>
      <demandValue>3.0</demandValue>
    </demand>
    <demand id="n2_D111">
      <source>n2_N8</source>
      <target>n2_N6</target>
      <demandValue>3.0</demandValue>
    </demand>
    <demand id="n2_D112">
      <source>n2_N8</source>
      <target>n2_N7</target>
      <demandValue>3.0</demandValue>
    </demand>
    <demand id="n2_D116">
      <source>n2_N8</source>
      <target>n2_N12</target>
      <demandValue>5.0</demandValue>
    </demand>
    <demand id="n2_D117">
      <source>n2_N8</source>
      <target>n2_N13</target>
      <demandValue>2.0</demandValue>
    </demand>
    <demand id="n2_D119">
      <source>n2_N8</source>
      <target>n2_N15</target>
      <demandValue>5.0</demandValue>
    </demand>
    <demand id="n2_D12">
      <source>n2_N1</source>
      <target>n2_N13</target>
      <demandValue>7.0</demandValue>
    </demand>
    <demand id="n2_D14">
      <source>n2_N1</source>
      <target>n2_N15</target>
      <demandValue>17.0</demandValue>
    </demand>
    <demand id="n2_D16">
      <source>n2_N2</source>
      <target>n2_N1</target>
      <demandValue>41.0</demandValue>
    </demand>
    <demand id="n2_D166">
      <source>n2_N12</source>
      <target>n2_N1</target>
      <demandValue>29.0</demandValue>
    </demand>
    <demand id="n2_D167">
      <source>n2_N12</source>
      <target>n2_N2</target>
      <demandValue>11.0</demandValue>
    </demand>
    <demand id="n2_D170">
      <source>n2_N12</source>
      <target>n2_N5</target>
      <demandValue>5.0</demandValue>
    </demand>
    <demand id="n2_D171">
      <source>n2_N12</source>
      <target>n2_N6</target>
      <demandValue>5.0</demandValue>
    </demand>
    <demand id="n2_D172">
      <source>n2_N12</source>
      <target>n2_N7</target>
      <demandValue>5.0</demandValue>
    </demand>
    <demand id="n2_D173">
      <source>n2_N12</source>
      <target>n2_N8</target>
      <demandValue>5.0</demandValue>
    </demand>
    <demand id="n2_D177">
      <source>n2_N12</source>
      <target>n2_N13</target>
      <demandValue>10.0</demandValue>
    </demand>
    <demand id="n2_D179">
      <source>n2_N12</source>
      <target>n2_N15</target>
      <demandValue>9.0</demandValue>
    </demand>
    <demand id="n2_D181">
      <source>n2_N13</source>
      <target>n2_N1</target>
      <demandValue>6.0</demandValue>
    </demand>
    <demand id="n2_D182">
      <source>n2_N13</source>
      <target>n2_N2</target>
      <demandValue>4.0</demandValue>
    </demand>
    <demand id="n2_D185">
      <source>n2_N13</source>
      <target>n2_N5</target>
      <demandValue>2.0</demandValue>
    </demand>
    <demand id="n2_D186">
      <source>n2_N13</source>
      <target>n2_N6</target>
      <demandValue>2.0</demandValue>
    </demand>
    <demand id="n2_D187">
      <source>n2_N13</source>
      <target>n2_N7</target>
      <demandValue>2.0</demandValue>
    </demand>
    <demand id="n2_D188">
      <source>n2_N13</source>
      <target>n2_N8</target>
      <demandValue>2.0</demandValue>
    </demand>
    <demand id="n2_D19">
      <source>n2_N2</source>
      <target>n2_N5</target>
      <demandValue>7.0</demandValue>
    </demand>
    <demand id="n2_D192">
      <source>n2_N13</source>
      <target>n2_N12</target>
      <demandValue>10.0</demandValue>
    </demand>
    <demand id="n2_D194">
      <source>n2_N13</source>
      <target>n2_N15</target>
      <demandValue>4.0</demandValue>
    </demand>
    <demand id="n2_D20">
      <source>n2_N2</source>
      <target>n2_N6</target>
      <demandValue>7.0</demandValue>
    </demand>
    <demand id="n2_D21">
      <source>n2_N2</source>
      <target>n2_N7</target>
      <demandValue>7.0</demandValue>
    </demand>
    <demand id="n2_D211">
      <source>n2_N15</source>
      <target>n2_N1</target>
      <demandValue>16.0</demandValue>
    </demand>
    <demand id="n2_D212">
      <source>n2_N15</source>
      <target>n2_N2</target>
      <demandValue>11.0</demandValue>
    </demand>
    <demand id="n2_D215">
      <source>n2_N15</source>
      <target>n2_N5</target>
      <demandValue>5.0</demandValue>
    </demand>
    <demand id="n2_D216">
      <source>n2_N15</source>
      <target>n2_N6</target>
      <demandValue>5.0</demandValue>
    </demand>
    <demand id="n2_D217">
      <source>n2_N15</source>
      <target>n2_N7</target>
      <demandValue>5.0</demandValue>
    </demand>
    <demand id="n2_D218">
      <source>n2_N15</source>
      <target>n2_N8</target>
      <demandValue>5.0</demandValue>
    </demand>
    <demand id="n2_D22">
      <source>n2_N2</source>
      <target>n2_N8</target>
      <demandValue>7.0</demandValue>
    </demand>
    <demand id="n2_D222">
      <source>n2_N15</source>
      <target>n2_N12</target>
      <demandValue>9.0</demandValue>
    </demand>
    <demand id="n2_D223">
      <source>n2_N15</source>
      <target>n2_N13</target>
      <demandValue>4.0</demandValue>
    </demand>
    <demand id="n2_D26">
      <source>n2_N2</source>
      <target>n2_N12</target>
      <demandValue>11.0</demandValue>
    </demand>
    <demand id="n2_D27">
      <source>n2_N2</source>
      <target>n2_N13</target>
      <demandValue>5.0</demandValue>
    </demand>
    <demand id="n2_D29">
      <source>n2_N2</source>
      <target>n2_N15</target>
      <demandValue>11.0</demandValue>
    </demand>
    <demand id="n2_D4">
      <source>n2_N1</source>
      <target>n2_N5</target>
      <demandValue>20.0</demandValue>
    </demand>
    <demand id="n2_D5">
      <source>n2_N1</source>
      <target>n2_N6</target>
      <demandValue>20.0</demandValue>
    </demand>
    <demand id="n2_D6">
      <source>n2_N1</source>
      <target>n2_N7</target>
      <demandValue>20.0</demandValue>
    </demand>
    <demand id="n2_D61">
      <source>n2_N5</source>
      <target>n2_N1</target>
      <demandValue>9.0</demandValue>
    </demand>
    <demand id="n2_D62">
      <source>n2_N5</source>
      <target>n2_N2</target>
      <demandValue>6.0</demandValue>
    </demand>
    <demand id="n2_D65">
      <source>n2_N5</source>
      <target>n2_N6</target>
      <demandValue>3.0</demandValue>
    </demand>
    <demand id="n2_D66">
      <source>n2_N5</source>
      <target>n2_N7</target>
      <demandValue>3.0</demandValue>
    </demand>
    <demand id="n2_D67">
      <source>n2_N5</source>
      <target>n2_N8</target>
      <demandValue>3.0</demandValue>
    </demand>
    <demand id="n2_D7">
      <source>n2_N1</source>
      <target>n2_N8</target>
      <demandValue>20.0</demandValue>
    </demand>
    <demand id="n2_D71">
      <source>n2_N5</source>
      <target>n2_N12</target>
      <demandValue>5.0</demandValue>
    </demand>
    <demand id="n2_D72">
      <source>n2_N5</source>
      <target>n2_N13</target>
      <demandValue>2.0</demandValue>
    </demand>
    <demand id="n2_D74">
      <source>n2_N5</source>
      <target>n2_N15</target>
      <demandValue>5.0</demandValue>
    </demand>
    <demand id="n2_D76">
      <source>n2_N6</source>
      <target>n2_N1</target>
      <demandValue>9.0</demandValue>
    </demand>
    <demand id="n2_D77">
      <source>n2_N6</source>
      <target>n2_N2</target>
      <demandValue>6.0</demandValue>
    </demand>
    <demand id="n2_D80">
      <source>n2_N6</source>
      <target>n2_N5</target>
      <demandValue>3.0</demandValue>
    </demand>
    <demand id="n2_D81">
      <source>n2_N6</source>
      <target>n2_N7</target>
      <demandValue>3.0</demandValue>
    </demand>
    <demand id="n2_D82">
      <source>n2_N6</source>
      <target>n2_N8</target>
      <demandValue>3.0</demandValue>
    </demand>
    <demand id="n2_D86">
      <source>n2_N6</source>
      <target>n2_N12</target>
      <demandValue>5.0</demandValue>
    </demand>
    <demand id="n2_D87">
      <source>n2_N6</source>
      <target>n2_N13</target>
      <demandValue>2.0</demandValue>
    </demand>
    <demand id="n2_D89">
      <source>n2_N6</source>
      <target>n2_N15</target>
      <demandValue>5.0</demandValue>
    </demand>
    <demand id="n2_D91">
      <source>n2_N7</source>
      <target>n2_N1</target>
      <demandValue>9.0</demandValue>
    </demand>
    <demand id="n2_D92">
      <source>n2_N7</source>
      <target>n2_N2</target>
      <demandValue>6.0</demandValue>
    </demand>
    <demand id="n2_D95">
      <source>n2_N7</source>
      <target>n2_N5</target>
      <demandValue>3.0</demandValue>
    </demand>
    <demand id="n2_D96">
      <source>n2_N7</source>
      <target>n2_N6</target>
      <demandValue>3.0</demandValue>
    </demand>
    <demand id="n2_D97">
      <source>n2_N7</source>
      <target>n2_N8</target>
      <demandValue>3.0</demandValue>
    </demand>
  </demands>
</network>
